ezsmdeploy/__init__.py
ezsmdeploy/modelscript_sklearn.py
ezsmdeploy/data/Dockerfile
ezsmdeploy/data/Dockerfile_flask
ezsmdeploy/data/build-docker.sh
ezsmdeploy/data/conversation.py
ezsmdeploy/data/cost.csv
ezsmdeploy/data/dockerd-entrypoint.py
ezsmdeploy/data/instancetypes.csv
ezsmdeploy/data/model_handler.py
ezsmdeploy/data/nginx.conf
ezsmdeploy/data/predictor.py
ezsmdeploy/data/serve
ezsmdeploy/data/smlocust.py
ezsmdeploy/data/train
ezsmdeploy/data/wsgi.py
ezsmdeploydev-1.100.dev0.dist-info/METADATA
ezsmdeploydev-1.100.dev0.dist-info/WHEEL
ezsmdeploydev-1.100.dev0.dist-info/top_level.txt
ezsmdeploydev-1.100.dev0.dist-info/RECORD
