Metadata-Version: 2.1
Name: ezsmdeploydev
Version: 1.100.dev0
Summary: SageMaker custom deployments made easy
Home-page: https://pypi.python.org/pypi/ezsmdeploy
Author: Shreyas Subramanian
Author-email: subshrey@amazon.com
License: MIT
Classifier: Development Status :: 3 - Alpha
Classifier: Intended Audience :: Developers
Classifier: Natural Language :: English
Classifier: License :: OSI Approved :: Apache Software License
Classifier: Programming Language :: Python
Requires-Dist: sagemaker (==2.173.0)
Requires-Dist: yaspin (==0.16.0)
Requires-Dist: shortuuid (==1.0.1)
Requires-Dist: sagemaker-studio-image-build (==0.5.0)
Requires-Dist: boto3 (>=1.14.12)
Provides-Extra: locust
Requires-Dist: locustio (==0.14.5) ; extra == 'locust'
